hdx_cli_toolkit/__init__.py
hdx_cli_toolkit/ckan_utilities.py
hdx_cli_toolkit/cli.py
hdx_cli_toolkit/data_quality_utilities.py
hdx_cli_toolkit/hapi_utilities.py
hdx_cli_toolkit/hdx_utilities.py
hdx_cli_toolkit/stable_schema_utilities.py
hdx_cli_toolkit/utilities.py
hdx_cli_toolkit/data/datagrid-datasets.csv
hdx_cli_toolkit-2025.8.1.dist-info/licenses/LICENSE
hdx_cli_toolkit-2025.8.1.dist-info/METADATA
hdx_cli_toolkit-2025.8.1.dist-info/WHEEL
hdx_cli_toolkit-2025.8.1.dist-info/entry_points.txt
hdx_cli_toolkit-2025.8.1.dist-info/top_level.txt
hdx_cli_toolkit-2025.8.1.dist-info/RECORD
