Metadata-Version: 2.4
Name: hdx_cli_toolkit
Version: 2025.8.1
Summary: HDX CLI tool kit for commandline interaction with HDX
Author: Ian Hopkinson
Author-email: ianhopkinson@googlemail.com
License: The MIT License (MIT)
Project-URL: repository, https://github.com/OCHA-DAP/hdx-cli-toolkit
Requires-Python: >=3.11
License-File: LICENSE
Requires-Dist: hdx-python-api==6.3.1
Requires-Dist: hdx-python-country
Requires-Dist: ckanapi
Requires-Dist: libhxl==5.2.2
Requires-Dist: quantulum3[classifier]
Requires-Dist: click
Requires-Dist: hatch
Requires-Dist: pytest
Requires-Dist: pytest-cov
Requires-Dist: black==23.10.0
Requires-Dist: flake8
Requires-Dist: pylint
Dynamic: license-file
